DjangoScrubber/DjangoScrubber.py
DjangoScrubber/__init__.py
django_project_scrubber-0.1.9.dist-info/LICENSE
django_project_scrubber-0.1.9.dist-info/METADATA
django_project_scrubber-0.1.9.dist-info/WHEEL
django_project_scrubber-0.1.9.dist-info/entry_points.txt
django_project_scrubber-0.1.9.dist-info/top_level.txt
django_project_scrubber-0.1.9.dist-info/RECORD
