Metadata-Version: 2.1
Name: django-project-scrubber
Version: 0.1.9
Summary: A tool to analyze Django projects for unused components
Home-page: https://github.com/HappyMinsker/DjangoScrubber
Author: HappyMinsker
Author-email: daniit.system@gmail.com
Classifier: Development Status :: 3 - Alpha
Classifier: Intended Audience :: Developers
Classifier: License :: OSI Approved :: MIT License
Classifier: Programming Language :: Python :: 3
Classifier: Programming Language :: Python :: 3.8
Classifier: Programming Language :: Python :: 3.9
Classifier: Programming Language :: Python :: 3.10
Classifier: Programming Language :: Python :: 3.11
Requires-Python: >=3.8
License-File: LICENSE
Requires-Dist: Django>=3.0
Requires-Dist: click>=8.0
